annofetch/__init__.py
annofetch/main.py
annofetch/Example/README.md
annofetch/Example/test_accessions.txt
annofetch/lib/__init__.py
annofetch/lib/myIO.py
annofetch/lib/protocols.py
annofetch/lib/regex.py
annofetch/lib/type.py
annofetch/lib/configuration/__init__.py
annofetch/lib/configuration/config.ini
annofetch/lib/configuration/config.py
annofetch/lib/database/__init__.py
annofetch/lib/database/cog.py
annofetch/lib/database/cognames_function.tab
annofetch/lib/database/ena.py
annofetch/lib/database/fun2003-2014.tab
annofetch/lib/database/geneOntology.py
annofetch/lib/database/hgnc.py
annofetch/lib/database/ncbi.py
annofetch/lib/database/uniprot.py
annofetch/lib/exception/__init__.py
annofetch/lib/exception/accession_error.py
annofetch/lib/exception/config_error.py
annofetch-1.0.0.data/data/annofetch/Example/README.md
annofetch-1.0.0.data/data/annofetch/Example/test_accessions.txt
annofetch-1.0.0.dist-info/LICENSE.txt
annofetch-1.0.0.dist-info/METADATA
annofetch-1.0.0.dist-info/WHEEL
annofetch-1.0.0.dist-info/entry_points.txt
annofetch-1.0.0.dist-info/top_level.txt
annofetch-1.0.0.dist-info/RECORD
