Metadata-Version: 2.1
Name: annofetch
Version: 1.0.0
Summary: Command Line Script to fetch annotations.
Home-page: UNKNOWN
Author: Sarah Kasemann
Author-email: sarah.kasemann@uni-bielefeld.de
License: GPL
Keywords: accession fetching annotations
Platform: UNKNOWN
Classifier: Programming Language :: Python :: 3
Classifier: License :: OSI Approved :: MIT License
Classifier: Operating System :: OS Independent
Requires-Dist: biopython
Requires-Dist: requests
